common_dates/__init__.py
common_dates/common_dates.py
common_dates-0.0.2.dist-info/METADATA
common_dates-0.0.2.dist-info/WHEEL
common_dates-0.0.2.dist-info/licenses/LICENSE
common_dates-0.0.2.dist-info/RECORD
