Metadata-Version: 2.1
Name: common_dates
Version: 0.0.2
Summary: A simple library for generating dates in common scenarios for data analysis.
Project-URL: Homepage, https://github.com/scienceindata/common_dates
Project-URL: Bug Tracker, https://github.com/scienceindata/common_dates/issues
Author: Science in Data
License-File: LICENSE
Classifier: License :: OSI Approved :: MIT License
Classifier: Operating System :: OS Independent
Classifier: Programming Language :: Python :: 3
Requires-Python: >=3.0
